udk_configparser/__init__.py
udk_configparser/_version.py
udk_configparser/udk_configparser.py
udk_configparser-1.1.1.dist-info/METADATA
udk_configparser-1.1.1.dist-info/WHEEL
udk_configparser-1.1.1.dist-info/licenses/LICENSE
udk_configparser-1.1.1.dist-info/RECORD
