Metadata-Version: 2.1
Name: udk_configparser
Version: 1.1.1
Summary: Config parser for UDK .ini files.
Project-URL: Homepage, https://github.com/tuokri/udk_configparser/
Author-email: Tuomo Kriikkula <tuokri@tuta.io>
License-Expression: MIT
License-File: LICENSE
Classifier: License :: OSI Approved :: MIT License
Classifier: Operating System :: OS Independent
Classifier: Programming Language :: Python :: 3.6
Classifier: Programming Language :: Python :: 3.7
Classifier: Programming Language :: Python :: 3.8
Classifier: Programming Language :: Python :: 3.9
Classifier: Programming Language :: Python :: 3.10
Classifier: Programming Language :: Python :: 3.11
Classifier: Programming Language :: Python :: 3.12
Requires-Python: >=3.6
